python_ethermine/__init__.py
python_ethermine/base_client.py
python_ethermine/ethermine_client.py
python_ethermine/controllers/__init__.py
python_ethermine/controllers/miner.py
python_ethermine/controllers/pool.py
python_ethermine/controllers/worker.py
python_ethermine/models/__init__.py
python_ethermine/models/miner/__init__.py
python_ethermine/models/miner/dashboard.py
python_ethermine/models/miner/history.py
python_ethermine/models/miner/payouts.py
python_ethermine/models/miner/rounds.py
python_ethermine/models/miner/settings.py
python_ethermine/models/miner/statistic.py
python_ethermine/models/pool/__init__.py
python_ethermine/models/pool/basic_pool_stats.py
python_ethermine/models/pool/mined_blocks_stats.py
python_ethermine/models/pool/network_statistics.py
python_ethermine/models/pool/server_hashrate_stats.py
python_ethermine/models/worker/__init__.py
python_ethermine/models/worker/all_worker_stats.py
python_ethermine/models/worker/individual_historical_worker_stats.py
python_ethermine/models/worker/individual_worker_stats.py
python_ethermine/models/worker/worker_monitoring.py
python_ethermine-0.0.2.dist-info/LICENSE
python_ethermine-0.0.2.dist-info/METADATA
python_ethermine-0.0.2.dist-info/WHEEL
python_ethermine-0.0.2.dist-info/top_level.txt
python_ethermine-0.0.2.dist-info/RECORD
