Metadata-Version: 2.1
Name: python-ethermine
Version: 0.0.2
Summary: Ethermine API wrapper
Home-page: https://github.com/tekgeek88/python-ethermine
Author: Carl Argabright
Author-email: carl.argabright@gmail.com
License: UNKNOWN
Project-URL: Bug Tracker, https://github.com/tekgeek88/python-ethermine/issues
Platform: UNKNOWN
Classifier: Programming Language :: Python :: 3
Classifier: License :: OSI Approved :: MIT License
Classifier: Operating System :: OS Independent
Requires-Python: >=3.6
License-File: LICENSE
Requires-Dist: requests
